discordpython/__init__.py
discordpython/setup.py
discordpython-0.0.2.dist-info/METADATA
discordpython-0.0.2.dist-info/WHEEL
discordpython-0.0.2.dist-info/top_level.txt
discordpython-0.0.2.dist-info/RECORD
